Metadata-Version: 1.1
Name: django-bootstrap3-datetimepicker
Version: 2.2.0
Summary: Bootstrap3 compatible datetimepicker for Django projects.
Home-page: https://github.com/nkunihiko/django-bootstrap3-datetimepicker
Author: Nakahara Kunihiko
Author-email: nakahara.kunihiko@gmail.com
License: Apache License 2.0
Platform: UNKNOWN
Classifier: Intended Audience :: Developers
Classifier: License :: OSI Approved :: Apache Software License
Classifier: Programming Language :: Python
Classifier: Programming Language :: Python :: 2
Classifier: Programming Language :: Python :: 3
Classifier: Operating System :: OS Independent
Classifier: Topic :: Software Development :: Libraries
Classifier: Topic :: Utilities
Classifier: Environment :: Web Environment
Classifier: Framework :: Django
